karrio_cli/__init__.py
karrio_cli/__main__.py
karrio_cli/commands/__init__.py
karrio_cli/commands/codegen.py
karrio_cli/commands/login.py
karrio_cli/commands/plugins.py
karrio_cli/commands/sdk.py
karrio_cli/commands/studio.py
karrio_cli/common/queries.py
karrio_cli/common/utils.py
karrio_cli/resources/__init__.py
karrio_cli/resources/carriers.py
karrio_cli/resources/connections.py
karrio_cli/resources/events.py
karrio_cli/resources/logs.py
karrio_cli/resources/orders.py
karrio_cli/resources/shipments.py
karrio_cli/resources/trackers.py
karrio_cli/skills/__init__.py
karrio_cli/skills/carrier-integration/instructions.md
karrio_cli/skills/carrier-integration/skill.json
karrio_cli/skills/carrier-integration/examples/duties_insurance_implementation.py
karrio_cli/skills/carrier-integration/examples/error_proxy_settings_patterns.py
karrio_cli/skills/carrier-integration/examples/lib_reference.py
karrio_cli/skills/carrier-integration/examples/manifest_document_address_implementation.py
karrio_cli/skills/carrier-integration/examples/models_reference.py
karrio_cli/skills/carrier-integration/examples/pickup_implementation.py
karrio_cli/skills/carrier-integration/examples/rate_implementation.py
karrio_cli/skills/carrier-integration/examples/shipment_implementation.py
karrio_cli/skills/carrier-integration/examples/tracking_implementation.py
karrio_cli/skills/carrier-integration/examples/units_template.py
karrio_cli/skills/carrier-integration/examples/webhook_oauth_implementation.py
karrio_cli/studio_ui/action_result.html
karrio_cli/studio_ui/dashboard.html
karrio_cli/studio_ui/extension.html
karrio_cli/studio_ui/index.html
karrio_cli/studio_ui/new_extension.html
karrio_cli/studio_ui/sidebar_extensions.html
karrio_cli/templates/__init__.py
karrio_cli/templates/address.py
karrio_cli/templates/docs.py
karrio_cli/templates/documents.py
karrio_cli/templates/duties.py
karrio_cli/templates/hooks.py
karrio_cli/templates/insurance.py
karrio_cli/templates/manifest.py
karrio_cli-2026.1.4.dist-info/METADATA
karrio_cli-2026.1.4.dist-info/WHEEL
karrio_cli-2026.1.4.dist-info/entry_points.txt
karrio_cli-2026.1.4.dist-info/top_level.txt
karrio_cli-2026.1.4.dist-info/RECORD
