Metadata-Version: 2.4
Name: karrio-cli
Version: 2026.1.4
Summary: Command line interface for Karrio
Author-email: Karrio Team <hello@karrio.io>
License: MIT
Project-URL: Homepage, https://github.com/karrioapi/karrio
Project-URL: Bug Tracker, https://github.com/karrioapi/karrio/issues
Classifier: Programming Language :: Python :: 3
Classifier: Programming Language :: Python :: 3.11
Classifier: License :: OSI Approved :: MIT License
Classifier: Operating System :: OS Independent
Requires-Python: >=3.11
Requires-Dist: typer>=0.7.0
Requires-Dist: rich>=13.0.0
Requires-Dist: requests>=2.28.0
Requires-Dist: importlib-metadata>=4.12.0
Requires-Dist: jstruct>=0.1.0
Requires-Dist: generateDS
Requires-Dist: tabulate
Requires-Dist: Jinja2
Requires-Dist: fastapi
Requires-Dist: uvicorn
Requires-Dist: python-multipart
Provides-Extra: dev
Requires-Dist: python-dotenv; extra == "dev"
Requires-Dist: karrio; extra == "dev"
Requires-Dist: beautifulsoup4; extra == "dev"
Requires-Dist: pdfplumber; extra == "dev"
